sillymap
