Metadata-Version: 1.0
Name: sillymap
Version: 0.1.0
Summary: A silly implementation of a short read mapper for the course DD3436.
Home-page: http://github.com/alneberg/sillymap
Author: Johannes Alneberg
Author-email: alneberg@kth.se
License: MIT
Platform: UNKNOWN
